pyarcscripts/__init__.py
pyarcscripts/config.py
pyarcscripts/encryption.py
pyarcscripts/exception.py
pyarcscripts/file.py
pyarcscripts/logger.py
pyarcscripts/string.py
pyarcscripts/utils.py
pyarcscripts/versionning.py
tests/__init__.py
tests/logger.py
tests/string.py
pyarcscripts-0.0.9.dist-info/LICENSE
pyarcscripts-0.0.9.dist-info/METADATA
pyarcscripts-0.0.9.dist-info/WHEEL
pyarcscripts-0.0.9.dist-info/top_level.txt
pyarcscripts-0.0.9.dist-info/RECORD
