Metadata-Version: 2.1
Name: pyarcscripts
Version: 0.0.9
Summary: Paquetage Python qui stocke toutes les fonctionnalités utiles de pyArc pouvant être utilisé dans tous projets et modules pyArc
Home-page: https://github.com/inicode_celestin03/pyarcscripts
Author: INICODE
Author-email: contact.inicode@gmail.com
License: UNKNOWN
Platform: UNKNOWN
Classifier: Programming Language :: Python :: 3
Classifier: License :: OSI Approved :: MIT License
Classifier: Operating System :: OS Independent
Requires-Python: >=3.7
License-File: LICENSE
Requires-Dist: python-multipart (>=0.0.5)
